cursive_re/__init__.py
cursive_re/exprs.py
cursive_re-0.0.4.dist-info/LICENSE
cursive_re-0.0.4.dist-info/METADATA
cursive_re-0.0.4.dist-info/WHEEL
cursive_re-0.0.4.dist-info/top_level.txt
cursive_re-0.0.4.dist-info/RECORD
