Metadata-Version: 2.1
Name: cursive-re
Version: 0.0.4
Summary: Readable regular expressions for Python 3.6 and up.
Home-page: UNKNOWN
Author: Bogdan Popa
Author-email: bogdan@defn.io
License: UNKNOWN
Platform: UNKNOWN
Requires-Python: >=3.6
Provides-Extra: dev
Requires-Dist: flake8; extra == 'dev'
Requires-Dist: flake8-bugbear; extra == 'dev'
Requires-Dist: flake8-quotes; extra == 'dev'
Requires-Dist: isort; extra == 'dev'
Requires-Dist: bumpversion; extra == 'dev'
Requires-Dist: mypy; extra == 'dev'
Requires-Dist: twine; extra == 'dev'
Requires-Dist: pytest; extra == 'dev'
Requires-Dist: pytest-cov; extra == 'dev'
